CHANGES.txt
MANIFEST.in
README.rst
README.txt
setup.py
worldbuild/__init__.py
worldbuild/aikif_agent_explore.py
worldbuild/build_random_grid.py
worldbuild/cls_interface_application.py
worldbuild/config.py
worldbuild/convert_grid_to_tiled_map.py
worldbuild/convert_map_to_data.py
worldbuild/dungeon_generator.py
worldbuild/html_utils.py
worldbuild/image_utils.py
worldbuild/mcrcon.py
worldbuild/pathfind.py
worldbuild/sample.py
worldbuild/structures.py
worldbuild/wiki.py
worldbuild/world_builder.py
worldbuild.egg-info/PKG-INFO
worldbuild.egg-info/SOURCES.txt
worldbuild.egg-info/dependency_links.txt
worldbuild.egg-info/requires.txt
worldbuild.egg-info/top_level.txt
worldbuild/data/__init__.py
worldbuild/data/map-legends.jpg
worldbuild/data/sample_world.txt
worldbuild/data/world_traversed.txt
worldbuild/samples/ascii_runeset.tsx
worldbuild/samples/dungeon.sample
worldbuild/samples/dungeon.tmx
worldbuild/samples/dungeon_box2.sample
worldbuild/samples/dungeon_map_solved_v1.txt
worldbuild/samples/dungeon_map_solved_v2.txt
worldbuild/samples/dungeon_map_solved_v3.txt
worldbuild/samples/dungeon_resized_in_Tiled.png
worldbuild/samples/earth.yaml
worldbuild/samples/game.yaml
worldbuild/samples/test_world.tmx
worldbuild/samples/test_world.txt
worldbuild/samples/tiny_world.yaml
worldbuild/samples/alrona/alrona-pen-coloured-grid.jpg
worldbuild/samples/alrona/alrona-pen-coloured.jpg
worldbuild/samples/alrona/alrona-pen.jpg
worldbuild/samples/alrona/alrona.yaml
worldbuild/samples/alrona/alrona_history.rst
worldbuild/samples/alrona/animal-fliks.jpg
worldbuild/samples/alrona/animal-melps.jpg
worldbuild/samples/alrona/animal-razan.jpg
worldbuild/samples/alrona/helron-islands.jpg
worldbuild/samples/alrona/helron-outline.jpg
worldbuild/samples/alrona/paper-texture.jpg
worldbuild/samples/alrona/race-blumps.jpg
worldbuild/samples/alrona/sharnia.jpg
worldbuild/samples/alrona/story_ancient_annihilation.rst
worldbuild/samples/alrona/story_no_escape_from_helron.rst
worldbuild/samples/alrona/worldbuild.css
worldbuild/samples/alrona/z_orig_alrona_bw_map.jpg
worldbuild/samples/alrona/zinad.jpg
worldbuild/samples/alrona/wiki_op/Alrona.html
