Metadata-Version: 1.1
Name: worldbuild
Version: 0.0.8
Summary: Tools for computational world building
Home-page: https://github.com/acutesoftware/worldbuild
Author: Duncan Murray
Author-email: djmurray@acutesoftware.com.au
License: GNU General Public License v3 (GPLv3)
Platform: UNKNOWN
Classifier: Development Status :: 3 - Alpha
Classifier: Programming Language :: Python :: 3
Classifier: Programming Language :: Python :: 3.4
Classifier: Intended Audience :: Developers
Classifier: Natural Language :: English
Classifier: Operating System :: OS Independent
Classifier: Topic :: Software Development :: Libraries :: Python Modules
Classifier: Topic :: Games/Entertainment :: Simulation
Classifier: Topic :: Scientific/Engineering :: Artificial Life
